{
    "hash": "946206e783b8b9615b1efb11e10b18d2", 
    "thumb_exists": false, 
    "bytes": 0, 
    "path": "/", 
    "is_dir": true, 
    "icon": "folder", 
    "root": "dropbox", 
    "contents": [
        {
            "size": "0 bytes", 
            "rev": "a7630471f2ee", 
            "thumb_exists": false, 
            "bytes": 0, 
            "modified": "Tue, 18 Mar 2014 15:37:32 +0000", 
            "path": "/2014 Calendar", 
            "is_dir": true, 
            "icon": "folder_user", 
            "root": "dropbox", 
            "revision": 42851
        }, 
        {
            "size": "57.9 KB", 
            "rev": "6c9e0471f2ee", 
            "thumb_exists": true, 
            "bytes": 59239, 
            "modified": "Sat, 29 Jun 2013 20:00:34 +0000", 
            "mime_type": "image/jpeg", 
            "path": "/1011195_10201325801378213_474571616_n.jpg", 
            "is_dir": false, 
            "icon": "page_white_picture", 
            "root": "dropbox", 
            "client_mtime": "Sat, 29 Jun 2013 20:00:13 +0000", 
            "revision": 27806
        }, 
        {
            "size": "1 MB", 
            "rev": "711b0471f2ee", 
            "thumb_exists": true, 
            "bytes": 1085199, 
            "modified": "Tue, 12 Nov 2013 11:49:13 +0000", 
            "mime_type": "image/jpeg", 
            "path": "/________.JPG", 
            "is_dir": false, 
            "icon": "page_white_picture", 
            "root": "dropbox", 
            "client_mtime": "Mon, 11 Nov 2013 20:40:49 +0000", 
            "revision": 28955
        }, 
        {
            "size": "2.8 MB", 
            "rev": "711f0471f2ee", 
            "thumb_exists": true, 
            "bytes": 2886497, 
            "modified": "Thu, 21 Nov 2013 05:46:07 +0000", 
            "mime_type": "image/jpeg", 
            "path": "/_DSC0102.jpg", 
            "is_dir": false, 
            "icon": "page_white_picture", 
            "root": "dropbox", 
            "client_mtime": "Thu, 21 Nov 2013 05:45:09 +0000", 
            "revision": 28959
        }, 
        {
            "size": "0 bytes", 
            "rev": "8aaf0471f2ee", 
            "thumb_exists": false, 
            "bytes": 0, 
            "modified": "Tue, 04 Mar 2014 22:30:07 +0000", 
            "path": "/.git", 
            "is_dir": true, 
            "icon": "folder", 
            "root": "dropbox", 
            "revision": 35503
        }, 
        {
            "size": "26 bytes", 
            "rev": "8d850471f2ee", 
            "thumb_exists": false, 
            "bytes": 26, 
            "modified": "Tue, 04 Mar 2014 22:31:04 +0000", 
            "mime_type": "application/octet-stream", 
            "path": "/.gitignore", 
            "is_dir": false, 
            "icon": "page_white", 
            "root": "dropbox", 
            "client_mtime": "Tue, 04 Mar 2014 22:29:59 +0000", 
            "revision": 36229
        }, 
        {
            "size": "1.2 KB", 
            "rev": "8d860471f2ee", 
            "thumb_exists": false, 
            "bytes": 1202, 
            "modified": "Tue, 04 Mar 2014 22:31:04 +0000", 
            "mime_type": "application/octet-stream", 
            "path": "/.gitmodules", 
            "is_dir": false, 
            "icon": "page_white", 
            "root": "dropbox", 
            "client_mtime": "Tue, 04 Mar 2014 22:29:59 +0000", 
            "revision": 36230
        }, 
        {
            "size": "94 bytes", 
            "rev": "8d820471f2ee", 
            "thumb_exists": false, 
            "bytes": 94, 
            "modified": "Tue, 04 Mar 2014 22:31:04 +0000", 
            "mime_type": "application/octet-stream", 
            "path": "/.jshintrc", 
            "is_dir": false, 
            "icon": "page_white", 
            "root": "dropbox", 
            "client_mtime": "Tue, 04 Mar 2014 22:29:59 +0000", 
            "revision": 36226
        }, 
        {
            "size": "256 bytes", 
            "rev": "8d840471f2ee", 
            "thumb_exists": false, 
            "bytes": 256, 
            "modified": "Tue, 04 Mar 2014 22:31:04 +0000", 
            "mime_type": "application/octet-stream", 
            "path": "/.netrwhist", 
            "is_dir": false, 
            "icon": "page_white", 
            "root": "dropbox", 
            "client_mtime": "Tue, 04 Mar 2014 22:29:59 +0000", 
            "revision": 36228
        }, 
        {
            "size": "0 bytes", 
            "rev": "8a940471f2ee", 
            "thumb_exists": false, 
            "bytes": 0, 
            "modified": "Sun, 02 Mar 2014 01:08:57 +0000", 
            "path": "/Adam_Scott", 
            "is_dir": true, 
            "icon": "folder_user", 
            "root": "dropbox", 
            "revision": 35476
        }, 
        {
            "size": "0 bytes", 
            "rev": "c0290471f2ee", 
            "thumb_exists": false, 
            "bytes": 0, 
            "modified": "Sun, 20 Jul 2014 22:10:56 +0000", 
            "path": "/Airborne_Imagery_Finished", 
            "is_dir": true, 
            "icon": "folder", 
            "root": "dropbox", 
            "revision": 49193
        }, 
        {
            "size": "65.9 MB", 
            "rev": "ba610471f2ee", 
            "thumb_exists": false, 
            "bytes": 69128624, 
            "modified": "Fri, 09 May 2014 20:14:10 +0000", 
            "mime_type": "text/plain", 
            "path": "/allCountries.txt", 
            "is_dir": false, 
            "icon": "page_white_text", 
            "root": "dropbox", 
            "client_mtime": "Tue, 06 May 2014 12:00:56 +0000", 
            "revision": 47713
        }, 
        {
            "size": "0 bytes", 
            "rev": "b0471f2ee", 
            "thumb_exists": false, 
            "bytes": 0, 
            "modified": "Mon, 27 Feb 2012 17:36:35 +0000", 
            "path": "/Apps", 
            "is_dir": true, 
            "icon": "folder", 
            "root": "dropbox", 
            "revision": 11
        }, 
        {
            "size": "1.2 MB", 
            "rev": "67be0471f2ee", 
            "thumb_exists": true, 
            "bytes": 1274482, 
            "modified": "Sat, 20 Apr 2013 16:30:49 +0000", 
            "mime_type": "image/jpeg", 
            "path": "/Atkins Monster.jpg", 
            "is_dir": false, 
            "icon": "page_white_picture", 
            "root": "dropbox", 
            "client_mtime": "Thu, 31 May 2012 01:50:32 +0000", 
            "revision": 26558
        }, 
        {
            "size": "0 bytes", 
            "rev": "8b3c0471f2ee", 
            "thumb_exists": false, 
            "bytes": 0, 
            "modified": "Tue, 04 Mar 2014 22:30:11 +0000", 
            "path": "/autoload", 
            "is_dir": true, 
            "icon": "folder", 
            "root": "dropbox", 
            "revision": 35644
        }, 
        {
            "size": "1.2 KB", 
            "rev": "6cd90471f2ee", 
            "thumb_exists": false, 
            "bytes": 1238, 
            "modified": "Wed, 07 Aug 2013 20:35:48 +0000", 
            "mime_type": "application/octet-stream", 
            "path": "/backup_known_hosts", 
            "is_dir": false, 
            "icon": "page_white", 
            "root": "dropbox", 
            "client_mtime": "Wed, 07 Aug 2013 20:35:46 +0000", 
            "revision": 27865
        }, 
        {
            "size": "0 bytes", 
            "rev": "b9dd0471f2ee", 
            "thumb_exists": false, 
            "bytes": 0, 
            "modified": "Sat, 03 May 2014 00:05:36 +0000", 
            "path": "/backyardStuff", 
            "is_dir": true, 
            "icon": "folder", 
            "root": "dropbox", 
            "revision": 47581
        }, 
        {
            "size": "0 bytes", 
            "rev": "599b0471f2ee", 
            "thumb_exists": false, 
            "bytes": 0, 
            "modified": "Sun, 16 Sep 2012 15:27:33 +0000", 
            "path": "/blimp project", 
            "is_dir": true, 
            "icon": "folder", 
            "root": "dropbox", 
            "revision": 22939
        }, 
        {
            "size": "2.1 KB", 
            "rev": "b1d70471f2ee", 
            "thumb_exists": false, 
            "bytes": 2180, 
            "modified": "Wed, 02 Apr 2014 02:23:54 +0000", 
            "mime_type": "text/plain", 
            "path": "/blimp_todo.txt", 
            "is_dir": false, 
            "icon": "page_white_text", 
            "root": "dropbox", 
            "client_mtime": "Wed, 02 Apr 2014 02:23:52 +0000", 
            "revision": 45527
        }, 
        {
            "size": "0 bytes", 
            "rev": "a7980471f2ee", 
            "thumb_exists": false, 
            "bytes": 0, 
            "modified": "Thu, 27 Mar 2014 15:06:42 +0000", 
            "path": "/blimp_touchups", 
            "is_dir": true, 
            "icon": "folder", 
            "root": "dropbox", 
            "revision": 42904
        }, 
        {
            "size": "308 KB", 
            "rev": "6fee0471f2ee", 
            "thumb_exists": true, 
            "bytes": 315439, 
            "modified": "Sat, 14 Sep 2013 18:59:09 +0000", 
            "mime_type": "image/png", 
            "path": "/blimp_ui_screenshot.png", 
            "is_dir": false, 
            "icon": "page_white_picture", 
            "root": "dropbox", 
            "client_mtime": "Sat, 14 Sep 2013 18:58:58 +0000", 
            "revision": 28654
        }, 
        {
            "size": "7 KB", 
            "rev": "be700471f2ee", 
            "thumb_exists": false, 
            "bytes": 7146, 
            "modified": "Fri, 20 Jun 2014 04:07:23 +0000", 
            "mime_type": "text/html", 
            "path": "/blog_post.html", 
            "is_dir": false, 
            "icon": "page_white_code", 
            "root": "dropbox", 
            "client_mtime": "Fri, 20 Jun 2014 01:11:05 +0000", 
            "revision": 48752
        }, 
        {
            "size": "0 bytes", 
            "rev": "8b3b0471f2ee", 
            "thumb_exists": false, 
            "bytes": 0, 
            "modified": "Tue, 04 Mar 2014 22:30:11 +0000", 
            "path": "/bundle", 
            "is_dir": true, 
            "icon": "folder", 
            "root": "dropbox", 
            "revision": 35643
        }, 
        {
            "size": "397.5 KB", 
            "rev": "71230471f2ee", 
            "thumb_exists": true, 
            "bytes": 407021, 
            "modified": "Thu, 21 Nov 2013 06:35:07 +0000", 
            "mime_type": "image/jpeg", 
            "path": "/card4.jpg", 
            "is_dir": false, 
            "icon": "page_white_picture", 
            "root": "dropbox", 
            "client_mtime": "Thu, 21 Nov 2013 06:34:31 +0000", 
            "revision": 28963
        }, 
        {
            "size": "378.2 KB", 
            "rev": "71250471f2ee", 
            "thumb_exists": true, 
            "bytes": 387327, 
            "modified": "Thu, 21 Nov 2013 06:37:32 +0000", 
            "mime_type": "image/jpeg", 
            "path": "/card5.jpg", 
            "is_dir": false, 
            "icon": "page_white_picture", 
            "root": "dropbox", 
            "client_mtime": "Thu, 21 Nov 2013 06:35:59 +0000", 
            "revision": 28965
        }, 
        {
            "size": "553.9 KB", 
            "rev": "71270471f2ee", 
            "thumb_exists": true, 
            "bytes": 567229, 
            "modified": "Thu, 21 Nov 2013 07:04:14 +0000", 
            "mime_type": "image/jpeg", 
            "path": "/card_front.jpg", 
            "is_dir": false, 
            "icon": "page_white_picture", 
            "root": "dropbox", 
            "client_mtime": "Thu, 21 Nov 2013 07:03:59 +0000", 
            "revision": 28967
        }, 
        {
            "size": "0 bytes", 
            "rev": "443f0471f2ee", 
            "thumb_exists": false, 
            "bytes": 0, 
            "modified": "Mon, 04 Jun 2012 03:20:54 +0000", 
            "path": "/Code", 
            "is_dir": true, 
            "icon": "folder", 
            "root": "dropbox", 
            "revision": 17471
        }, 
        {
            "size": "0 bytes", 
            "rev": "6ce40471f2ee", 
            "thumb_exists": false, 
            "bytes": 0, 
            "modified": "Mon, 12 Aug 2013 03:07:12 +0000", 
            "path": "/Colin + Scott", 
            "is_dir": true, 
            "icon": "folder_user", 
            "root": "dropbox", 
            "revision": 27876
        }, 
        {
            "size": "164 bytes", 
            "rev": "6cd70471f2ee", 
            "thumb_exists": false, 
            "bytes": 164, 
            "modified": "Wed, 07 Aug 2013 20:35:48 +0000", 
            "mime_type": "application/octet-stream", 
            "path": "/config", 
            "is_dir": false, 
            "icon": "page_white", 
            "root": "dropbox", 
            "client_mtime": "Wed, 07 Aug 2013 20:35:46 +0000", 
            "revision": 27863
        }, 
        {
            "size": "0 bytes", 
            "rev": "71470471f2ee", 
            "thumb_exists": false, 
            "bytes": 0, 
            "modified": "Mon, 09 Dec 2013 23:14:42 +0000", 
            "path": "/CustomeSplice", 
            "is_dir": true, 
            "icon": "folder_user", 
            "root": "dropbox", 
            "revision": 28999
        }, 
        {
            "size": "0 bytes", 
            "rev": "72cc0471f2ee", 
            "thumb_exists": false, 
            "bytes": 0, 
            "modified": "Tue, 14 Jan 2014 21:27:33 +0000", 
            "path": "/Facial_Matching.key", 
            "is_dir": true, 
            "icon": "package", 
            "root": "dropbox", 
            "revision": 29388
        }, 
        {
            "size": "153 bytes", 
            "rev": "89f60471f2ee", 
            "thumb_exists": false, 
            "bytes": 153, 
            "modified": "Sun, 23 Feb 2014 12:04:17 +0000", 
            "mime_type": "text/plain", 
            "path": "/Git remote add scott ssh   your_repo.txt", 
            "is_dir": false, 
            "icon": "page_white_text", 
            "root": "dropbox", 
            "client_mtime": "Sun, 23 Feb 2014 12:04:15 +0000", 
            "revision": 35318
        }, 
        {
            "size": "131 bytes", 
            "rev": "a6ef0471f2ee", 
            "thumb_exists": false, 
            "bytes": 131, 
            "modified": "Fri, 07 Mar 2014 20:54:14 +0000", 
            "mime_type": "text/plain", 
            "path": "/helium_info.txt", 
            "is_dir": false, 
            "icon": "page_white_text", 
            "root": "dropbox", 
            "client_mtime": "Fri, 07 Mar 2014 20:53:30 +0000", 
            "revision": 42735
        }, 
        {
            "size": "17.5 KB", 
            "rev": "bfe90471f2ee", 
            "thumb_exists": false, 
            "bytes": 17872, 
            "modified": "Fri, 11 Jul 2014 20:40:43 +0000", 
            "mime_type": "application/octet-stream", 
            "path": "/json_response.json", 
            "is_dir": false, 
            "icon": "page_white_code", 
            "root": "dropbox", 
            "client_mtime": "Fri, 11 Jul 2014 20:40:49 +0000", 
            "revision": 49129
        }, 
        {
            "size": "2.8 KB", 
            "rev": "6cdb0471f2ee", 
            "thumb_exists": false, 
            "bytes": 2900, 
            "modified": "Wed, 07 Aug 2013 20:35:48 +0000", 
            "mime_type": "application/octet-stream", 
            "path": "/known_hosts", 
            "is_dir": false, 
            "icon": "page_white", 
            "root": "dropbox", 
            "client_mtime": "Wed, 07 Aug 2013 20:35:46 +0000", 
            "revision": 27867
        }, 
        {
            "size": "0 bytes", 
            "rev": "7a820471f2ee", 
            "thumb_exists": false, 
            "bytes": 0, 
            "modified": "Sun, 26 Jan 2014 04:26:18 +0000", 
            "path": "/live_face_detection", 
            "is_dir": true, 
            "icon": "folder", 
            "root": "dropbox", 
            "revision": 31362
        }, 
        {
            "size": "0 bytes", 
            "rev": "bf500471f2ee", 
            "thumb_exists": false, 
            "bytes": 0, 
            "modified": "Wed, 02 Jul 2014 00:38:53 +0000", 
            "path": "/Long Term Resume", 
            "is_dir": true, 
            "icon": "folder", 
            "root": "dropbox", 
            "revision": 48976
        }, 
        {
            "size": "0 bytes", 
            "rev": "bb9b0471f2ee", 
            "thumb_exists": false, 
            "bytes": 0, 
            "modified": "Wed, 04 Jun 2014 19:00:57 +0000", 
            "path": "/Lunch_learn.key", 
            "is_dir": true, 
            "icon": "package", 
            "root": "dropbox", 
            "revision": 48027
        }, 
        {
            "size": "1 KB", 
            "rev": "7d160471f2ee", 
            "thumb_exists": false, 
            "bytes": 1071, 
            "modified": "Mon, 03 Feb 2014 03:17:02 +0000", 
            "mime_type": "application/octet-stream", 
            "path": "/Makefile", 
            "is_dir": false, 
            "icon": "page_white", 
            "root": "dropbox", 
            "client_mtime": "Mon, 03 Feb 2014 03:17:10 +0000", 
            "revision": 32022
        }, 
        {
            "size": "51.3 KB", 
            "rev": "6cc40471f2ee", 
            "thumb_exists": true, 
            "bytes": 52522, 
            "modified": "Sat, 27 Jul 2013 20:07:17 +0000", 
            "mime_type": "image/jpeg", 
            "path": "/Medal.jpg", 
            "is_dir": false, 
            "icon": "page_white_picture", 
            "root": "dropbox", 
            "client_mtime": "Sat, 27 Jul 2013 20:06:55 +0000", 
            "revision": 27844
        }, 
        {
            "size": "64.6 KB", 
            "rev": "6ccb0471f2ee", 
            "thumb_exists": true, 
            "bytes": 66174, 
            "modified": "Mon, 29 Jul 2013 03:58:09 +0000", 
            "mime_type": "image/png", 
            "path": "/Medal.png", 
            "is_dir": false, 
            "icon": "page_white_picture", 
            "root": "dropbox", 
            "client_mtime": "Mon, 29 Jul 2013 03:58:06 +0000", 
            "revision": 27851
        }, 
        {
            "size": "0 bytes", 
            "rev": "be7c0471f2ee", 
            "thumb_exists": false, 
            "bytes": 0, 
            "modified": "Tue, 24 Jun 2014 19:11:20 +0000", 
            "path": "/mixpanel_guidelines.key", 
            "is_dir": true, 
            "icon": "package", 
            "root": "dropbox", 
            "revision": 48764
        }, 
        {
            "size": "271 KB", 
            "rev": "67bd0471f2ee", 
            "thumb_exists": true, 
            "bytes": 277527, 
            "modified": "Sat, 20 Apr 2013 16:30:49 +0000", 
            "mime_type": "image/jpeg", 
            "path": "/muscleCar2.jpg", 
            "is_dir": false, 
            "icon": "page_white_picture", 
            "root": "dropbox", 
            "client_mtime": "Fri, 25 Nov 2011 22:14:45 +0000", 
            "revision": 26557
        }, 
        {
            "size": "0 bytes", 
            "rev": "a72f0471f2ee", 
            "thumb_exists": false, 
            "bytes": 0, 
            "modified": "Thu, 13 Mar 2014 16:22:09 +0000", 
            "path": "/New folder", 
            "is_dir": true, 
            "icon": "folder", 
            "root": "dropbox", 
            "revision": 42799
        }, 
        {
            "size": "0 bytes", 
            "rev": "7db40471f2ee", 
            "thumb_exists": false, 
            "bytes": 0, 
            "modified": "Fri, 14 Feb 2014 05:08:08 +0000", 
            "path": "/opengl", 
            "is_dir": true, 
            "icon": "folder", 
            "root": "dropbox", 
            "revision": 32180
        }, 
        {
            "size": "354 bytes", 
            "rev": "c0010471f2ee", 
            "thumb_exists": false, 
            "bytes": 354, 
            "modified": "Wed, 16 Jul 2014 20:31:13 +0000", 
            "mime_type": "text/plain", 
            "path": "/payroll_info.txt", 
            "is_dir": false, 
            "icon": "page_white_text", 
            "root": "dropbox", 
            "client_mtime": "Wed, 16 Jul 2014 20:31:10 +0000", 
            "revision": 49153
        }, 
        {
            "size": "1.3 MB", 
            "rev": "67c50471f2ee", 
            "thumb_exists": true, 
            "bytes": 1312009, 
            "modified": "Sat, 20 Apr 2013 16:30:49 +0000", 
            "mime_type": "image/jpeg", 
            "path": "/Photo Jul 13, 7 48 30 AM.jpg", 
            "is_dir": false, 
            "icon": "page_white_picture", 
            "root": "dropbox", 
            "client_mtime": "Sun, 15 Jul 2012 17:06:16 +0000", 
            "revision": 26565
        }, 
        {
            "size": "100 KB", 
            "rev": "67ca0471f2ee", 
            "thumb_exists": true, 
            "bytes": 102400, 
            "modified": "Sat, 20 Apr 2013 16:30:49 +0000", 
            "mime_type": "image/jpeg", 
            "path": "/Photo Jun 12, 1 37 20 PM.jpg", 
            "is_dir": false, 
            "icon": "page_white_picture", 
            "root": "dropbox", 
            "client_mtime": "Sun, 15 Jul 2012 17:08:51 +0000", 
            "revision": 26570
        }, 
        {
            "size": "131.1 KB", 
            "rev": "67c70471f2ee", 
            "thumb_exists": true, 
            "bytes": 134244, 
            "modified": "Sat, 20 Apr 2013 16:30:49 +0000", 
            "mime_type": "image/png", 
            "path": "/Photo Jun 17, 4 17 23 PM.png", 
            "is_dir": false, 
            "icon": "page_white_picture", 
            "root": "dropbox", 
            "client_mtime": "Sun, 15 Jul 2012 17:08:26 +0000", 
            "revision": 26567
        }, 
        {
            "size": "112.5 KB", 
            "rev": "67c80471f2ee", 
            "thumb_exists": true, 
            "bytes": 115158, 
            "modified": "Sat, 20 Apr 2013 16:30:49 +0000", 
            "mime_type": "image/png", 
            "path": "/Photo Jun 17, 7 12 12 PM.png", 
            "is_dir": false, 
            "icon": "page_white_picture", 
            "root": "dropbox", 
            "client_mtime": "Sun, 15 Jul 2012 17:08:29 +0000", 
            "revision": 26568
        }, 
        {
            "size": "2.4 MB", 
            "rev": "67bf0471f2ee", 
            "thumb_exists": true, 
            "bytes": 2496354, 
            "modified": "Sat, 20 Apr 2013 16:30:49 +0000", 
            "mime_type": "image/jpeg", 
            "path": "/Photo May 21, 9 03 19 PM.jpg", 
            "is_dir": false, 
            "icon": "page_white_picture", 
            "root": "dropbox", 
            "client_mtime": "Sun, 15 Jul 2012 16:50:55 +0000", 
            "revision": 26559
        }, 
        {
            "size": "2.3 MB", 
            "rev": "67c00471f2ee", 
            "thumb_exists": true, 
            "bytes": 2447106, 
            "modified": "Sat, 20 Apr 2013 16:30:49 +0000", 
            "mime_type": "image/jpeg", 
            "path": "/Photo May 21, 9 03 25 PM.jpg", 
            "is_dir": false, 
            "icon": "page_white_picture", 
            "root": "dropbox", 
            "client_mtime": "Sun, 15 Jul 2012 16:51:08 +0000", 
            "revision": 26560
        }, 
        {
            "size": "2.1 MB", 
            "rev": "67c10471f2ee", 
            "thumb_exists": true, 
            "bytes": 2153406, 
            "modified": "Sat, 20 Apr 2013 16:30:49 +0000", 
            "mime_type": "image/jpeg", 
            "path": "/Photo May 22, 5 36 16 PM.jpg", 
            "is_dir": false, 
            "icon": "page_white_picture", 
            "root": "dropbox", 
            "client_mtime": "Sun, 15 Jul 2012 16:51:20 +0000", 
            "revision": 26561
        }, 
        {
            "size": "1.9 MB", 
            "rev": "67c20471f2ee", 
            "thumb_exists": true, 
            "bytes": 2032808, 
            "modified": "Sat, 20 Apr 2013 16:30:49 +0000", 
            "mime_type": "image/jpeg", 
            "path": "/Photo May 22, 5 37 03 PM.jpg", 
            "is_dir": false, 
            "icon": "page_white_picture", 
            "root": "dropbox", 
            "client_mtime": "Sun, 15 Jul 2012 16:51:31 +0000", 
            "revision": 26562
        }, 
        {
            "size": "2.2 MB", 
            "rev": "67c30471f2ee", 
            "thumb_exists": true, 
            "bytes": 2261056, 
            "modified": "Sat, 20 Apr 2013 16:30:49 +0000", 
            "mime_type": "image/jpeg", 
            "path": "/Photo May 22, 5 37 09 PM.jpg", 
            "is_dir": false, 
            "icon": "page_white_picture", 
            "root": "dropbox", 
            "client_mtime": "Sun, 15 Jul 2012 16:51:46 +0000", 
            "revision": 26563
        }, 
        {
            "size": "2 MB", 
            "rev": "67c40471f2ee", 
            "thumb_exists": true, 
            "bytes": 2048934, 
            "modified": "Sat, 20 Apr 2013 16:30:49 +0000", 
            "mime_type": "image/jpeg", 
            "path": "/Photo May 22, 5 37 36 PM.jpg", 
            "is_dir": false, 
            "icon": "page_white_picture", 
            "root": "dropbox", 
            "client_mtime": "Sun, 15 Jul 2012 16:51:57 +0000", 
            "revision": 26564
        }, 
        {
            "size": "152.4 KB", 
            "rev": "67c90471f2ee", 
            "thumb_exists": true, 
            "bytes": 156033, 
            "modified": "Sat, 20 Apr 2013 16:30:49 +0000", 
            "mime_type": "image/jpeg", 
            "path": "/Photo May 23, 10 02 39 AM.jpg", 
            "is_dir": false, 
            "icon": "page_white_picture", 
            "root": "dropbox", 
            "client_mtime": "Sun, 15 Jul 2012 17:08:41 +0000", 
            "revision": 26569
        }, 
        {
            "size": "1.5 MB", 
            "rev": "71100471f2ee", 
            "thumb_exists": true, 
            "bytes": 1584881, 
            "modified": "Sat, 09 Nov 2013 18:29:18 +0000", 
            "mime_type": "image/jpeg", 
            "path": "/Photo Nov 04, 3 29 39 PM.jpg", 
            "is_dir": false, 
            "icon": "page_white_picture", 
            "root": "dropbox", 
            "client_mtime": "Sat, 09 Nov 2013 18:29:18 +0000", 
            "revision": 28944
        }, 
        {
            "size": "2.6 MB", 
            "rev": "71110471f2ee", 
            "thumb_exists": true, 
            "bytes": 2741481, 
            "modified": "Sat, 09 Nov 2013 18:29:26 +0000", 
            "mime_type": "image/jpeg", 
            "path": "/Photo Nov 06, 1 35 18 AM.jpg", 
            "is_dir": false, 
            "icon": "page_white_picture", 
            "root": "dropbox", 
            "client_mtime": "Sat, 09 Nov 2013 18:29:26 +0000", 
            "revision": 28945
        }, 
        {
            "size": "2.3 MB", 
            "rev": "71120471f2ee", 
            "thumb_exists": true, 
            "bytes": 2458819, 
            "modified": "Sat, 09 Nov 2013 18:29:34 +0000", 
            "mime_type": "image/jpeg", 
            "path": "/Photo Nov 06, 6 44 04 PM.jpg", 
            "is_dir": false, 
            "icon": "page_white_picture", 
            "root": "dropbox", 
            "client_mtime": "Sat, 09 Nov 2013 18:29:34 +0000", 
            "revision": 28946
        }, 
        {
            "size": "2.4 MB", 
            "rev": "71140471f2ee", 
            "thumb_exists": true, 
            "bytes": 2522605, 
            "modified": "Sat, 09 Nov 2013 18:29:52 +0000", 
            "mime_type": "image/jpeg", 
            "path": "/Photo Nov 07, 3 00 19 PM.jpg", 
            "is_dir": false, 
            "icon": "page_white_picture", 
            "root": "dropbox", 
            "client_mtime": "Sat, 09 Nov 2013 18:29:52 +0000", 
            "revision": 28948
        }, 
        {
            "size": "3.3 MB", 
            "rev": "71130471f2ee", 
            "thumb_exists": true, 
            "bytes": 3508719, 
            "modified": "Sat, 09 Nov 2013 18:29:43 +0000", 
            "mime_type": "image/jpeg", 
            "path": "/Photo Nov 07, 9 44 20 AM.jpg", 
            "is_dir": false, 
            "icon": "page_white_picture", 
            "root": "dropbox", 
            "client_mtime": "Sat, 09 Nov 2013 18:29:44 +0000", 
            "revision": 28947
        }, 
        {
            "size": "1.8 MB", 
            "rev": "72c40471f2ee", 
            "thumb_exists": true, 
            "bytes": 1869331, 
            "modified": "Tue, 14 Jan 2014 08:02:20 +0000", 
            "mime_type": "image/jpeg", 
            "path": "/Photo Nov 08, 9 21 23 PM.jpg", 
            "is_dir": false, 
            "icon": "page_white_picture", 
            "root": "dropbox", 
            "client_mtime": "Tue, 14 Jan 2014 08:02:00 +0000", 
            "revision": 29380
        }, 
        {
            "size": "2 MB", 
            "rev": "71150471f2ee", 
            "thumb_exists": true, 
            "bytes": 2147231, 
            "modified": "Sat, 09 Nov 2013 18:29:57 +0000", 
            "mime_type": "image/jpeg", 
            "path": "/Photo Nov 09, 7 20 48 AM.jpg", 
            "is_dir": false, 
            "icon": "page_white_picture", 
            "root": "dropbox", 
            "client_mtime": "Sat, 09 Nov 2013 18:29:57 +0000", 
            "revision": 28949
        }, 
        {
            "size": "2 MB", 
            "rev": "71160471f2ee", 
            "thumb_exists": true, 
            "bytes": 2103672, 
            "modified": "Sat, 09 Nov 2013 18:30:03 +0000", 
            "mime_type": "image/jpeg", 
            "path": "/Photo Nov 09, 7 20 50 AM.jpg", 
            "is_dir": false, 
            "icon": "page_white_picture", 
            "root": "dropbox", 
            "client_mtime": "Sat, 09 Nov 2013 18:30:03 +0000", 
            "revision": 28950
        }, 
        {
            "size": "2 MB", 
            "rev": "71170471f2ee", 
            "thumb_exists": true, 
            "bytes": 2089307, 
            "modified": "Sat, 09 Nov 2013 18:30:14 +0000", 
            "mime_type": "image/jpeg", 
            "path": "/Photo Nov 09, 7 21 11 AM.jpg", 
            "is_dir": false, 
            "icon": "page_white_picture", 
            "root": "dropbox", 
            "client_mtime": "Sat, 09 Nov 2013 18:30:14 +0000", 
            "revision": 28951
        }, 
        {
            "size": "1.7 MB", 
            "rev": "71180471f2ee", 
            "thumb_exists": true, 
            "bytes": 1819797, 
            "modified": "Sat, 09 Nov 2013 18:30:19 +0000", 
            "mime_type": "image/jpeg", 
            "path": "/Photo Nov 09, 9 41 14 AM.jpg", 
            "is_dir": false, 
            "icon": "page_white_picture", 
            "root": "dropbox", 
            "client_mtime": "Sat, 09 Nov 2013 18:30:19 +0000", 
            "revision": 28952
        }, 
        {
            "size": "472 bytes", 
            "rev": "6f3f0471f2ee", 
            "thumb_exists": false, 
            "bytes": 472, 
            "modified": "Thu, 05 Sep 2013 05:36:58 +0000", 
            "mime_type": "application/octet-stream", 
            "path": "/putty_public_key", 
            "is_dir": false, 
            "icon": "page_white", 
            "root": "dropbox", 
            "client_mtime": "Thu, 05 Sep 2013 05:36:34 +0000", 
            "revision": 28479
        }, 
        {
            "size": "0 bytes", 
            "rev": "b4570471f2ee", 
            "thumb_exists": false, 
            "bytes": 0, 
            "modified": "Thu, 10 Apr 2014 15:10:01 +0000", 
            "path": "/PyCon Resources", 
            "is_dir": true, 
            "icon": "folder_user", 
            "root": "dropbox", 
            "revision": 46167
        }, 
        {
            "size": "0 bytes", 
            "rev": "b4710471f2ee", 
            "thumb_exists": false, 
            "bytes": 0, 
            "modified": "Wed, 16 Apr 2014 00:00:58 +0000", 
            "path": "/pycon_actual", 
            "is_dir": true, 
            "icon": "folder", 
            "root": "dropbox", 
            "revision": 46193
        }, 
        {
            "size": "2.7 KB", 
            "rev": "8d830471f2ee", 
            "thumb_exists": false, 
            "bytes": 2804, 
            "modified": "Tue, 04 Mar 2014 22:31:04 +0000", 
            "mime_type": "application/octet-stream", 
            "path": "/README.md", 
            "is_dir": false, 
            "icon": "page_white_text", 
            "root": "dropbox", 
            "client_mtime": "Tue, 04 Mar 2014 22:29:59 +0000", 
            "revision": 36227
        }, 
        {
            "size": "505 bytes", 
            "rev": "b1d40471f2ee", 
            "thumb_exists": false, 
            "bytes": 505, 
            "modified": "Wed, 02 Apr 2014 00:31:44 +0000", 
            "mime_type": "text/plain", 
            "path": "/resources.txt", 
            "is_dir": false, 
            "icon": "page_white_text", 
            "root": "dropbox", 
            "client_mtime": "Wed, 02 Apr 2014 00:31:43 +0000", 
            "revision": 45524
        }, 
        {
            "size": "2.8 KB", 
            "rev": "c0270471f2ee", 
            "thumb_exists": false, 
            "bytes": 2870, 
            "modified": "Sun, 20 Jul 2014 22:09:59 +0000", 
            "mime_type": "text/x-python", 
            "path": "/sample_boto.py", 
            "is_dir": false, 
            "icon": "page_white_code", 
            "root": "dropbox", 
            "client_mtime": "Sun, 20 Jul 2014 22:09:59 +0000", 
            "revision": 49191
        }, 
        {
            "size": "0 bytes", 
            "rev": "8aac0471f2ee", 
            "thumb_exists": false, 
            "bytes": 0, 
            "modified": "Tue, 04 Mar 2014 04:42:33 +0000", 
            "path": "/sample_code", 
            "is_dir": true, 
            "icon": "folder", 
            "root": "dropbox", 
            "revision": 35500
        }, 
        {
            "size": "0 bytes", 
            "rev": "680b0471f2ee", 
            "thumb_exists": false, 
            "bytes": 0, 
            "modified": "Tue, 14 May 2013 15:27:03 +0000", 
            "path": "/Scott + Tom", 
            "is_dir": true, 
            "icon": "folder_user", 
            "root": "dropbox", 
            "revision": 26635
        }, 
        {
            "size": "0 bytes", 
            "rev": "8a820471f2ee", 
            "thumb_exists": false, 
            "bytes": 0, 
            "modified": "Sat, 01 Mar 2014 20:36:31 +0000", 
            "path": "/Scott_Chase", 
            "is_dir": true, 
            "icon": "folder_user", 
            "root": "dropbox", 
            "revision": 35458
        }, 
        {
            "size": "0 bytes", 
            "rev": "72b20471f2ee", 
            "thumb_exists": false, 
            "bytes": 0, 
            "modified": "Fri, 10 Jan 2014 07:50:05 +0000", 
            "path": "/Screenshots", 
            "is_dir": true, 
            "icon": "folder", 
            "root": "dropbox", 
            "revision": 29362
        }, 
        {
            "size": "0 bytes", 
            "rev": "680d0471f2ee", 
            "thumb_exists": false, 
            "bytes": 0, 
            "modified": "Tue, 14 May 2013 15:27:03 +0000", 
            "path": "/Shared Folder for Scott and Le", 
            "is_dir": true, 
            "icon": "folder_user", 
            "root": "dropbox", 
            "revision": 26637
        }, 
        {
            "size": "55.6 KB", 
            "rev": "71210471f2ee", 
            "thumb_exists": true, 
            "bytes": 56976, 
            "modified": "Thu, 21 Nov 2013 06:04:41 +0000", 
            "mime_type": "image/jpeg", 
            "path": "/SQL.JPG", 
            "is_dir": false, 
            "icon": "page_white_picture", 
            "root": "dropbox", 
            "client_mtime": "Thu, 21 Nov 2013 06:04:24 +0000", 
            "revision": 28961
        }, 
        {
            "size": "37 bytes", 
            "rev": "89d20471f2ee", 
            "thumb_exists": false, 
            "bytes": 37, 
            "modified": "Tue, 18 Feb 2014 17:57:24 +0000", 
            "mime_type": "text/plain", 
            "path": "/ssn_info.txt", 
            "is_dir": false, 
            "icon": "page_white_text", 
            "root": "dropbox", 
            "client_mtime": "Tue, 18 Feb 2014 17:58:11 +0000", 
            "revision": 35282
        }, 
        {
            "size": "0 bytes", 
            "rev": "607b0471f2ee", 
            "thumb_exists": false, 
            "bytes": 0, 
            "modified": "Wed, 13 Feb 2013 14:42:56 +0000", 
            "path": "/StickFigureFight", 
            "is_dir": true, 
            "icon": "folder", 
            "root": "dropbox", 
            "revision": 24699
        }, 
        {
            "size": "0 bytes", 
            "rev": "8bc40471f2ee", 
            "thumb_exists": false, 
            "bytes": 0, 
            "modified": "Tue, 04 Mar 2014 22:30:22 +0000", 
            "path": "/syntax", 
            "is_dir": true, 
            "icon": "folder", 
            "root": "dropbox", 
            "revision": 35780
        }, 
        {
            "size": "0 bytes", 
            "rev": "bf7c0471f2ee", 
            "thumb_exists": false, 
            "bytes": 0, 
            "modified": "Sun, 06 Jul 2014 20:30:34 +0000", 
            "path": "/tar_files", 
            "is_dir": true, 
            "icon": "folder", 
            "root": "dropbox", 
            "revision": 49020
        }, 
        {
            "size": "0 bytes", 
            "rev": "b1f70471f2ee", 
            "thumb_exists": false, 
            "bytes": 0, 
            "modified": "Thu, 03 Apr 2014 18:41:32 +0000", 
            "path": "/Taxes", 
            "is_dir": true, 
            "icon": "folder_user", 
            "root": "dropbox", 
            "revision": 45559
        }, 
        {
            "size": "0 bytes", 
            "rev": "7a650471f2ee", 
            "thumb_exists": false, 
            "bytes": 0, 
            "modified": "Sat, 25 Jan 2014 06:06:41 +0000", 
            "path": "/theme_music", 
            "is_dir": true, 
            "icon": "folder", 
            "root": "dropbox", 
            "revision": 31333
        }, 
        {
            "size": "3.8 KB", 
            "rev": "bad90471f2ee", 
            "thumb_exists": false, 
            "bytes": 3898, 
            "modified": "Thu, 22 May 2014 04:19:48 +0000", 
            "mime_type": "text/plain", 
            "path": "/todo (Scott-Lobdell-MBP15-tag-35's conflicted copy 2014-05-21).txt", 
            "is_dir": false, 
            "icon": "page_white_text", 
            "root": "dropbox", 
            "client_mtime": "Thu, 22 May 2014 00:57:40 +0000", 
            "revision": 47833
        }, 
        {
            "size": "8.6 KB", 
            "rev": "c0250471f2ee", 
            "thumb_exists": false, 
            "bytes": 8839, 
            "modified": "Sun, 20 Jul 2014 22:01:07 +0000", 
            "mime_type": "text/plain", 
            "path": "/todo.txt", 
            "is_dir": false, 
            "icon": "page_white_text", 
            "root": "dropbox", 
            "client_mtime": "Sun, 20 Jul 2014 22:01:05 +0000", 
            "revision": 49189
        }, 
        {
            "size": "22.6 KB", 
            "rev": "662a0471f2ee", 
            "thumb_exists": true, 
            "bytes": 23096, 
            "modified": "Sat, 20 Apr 2013 16:30:49 +0000", 
            "mime_type": "image/png", 
            "path": "/Untitled.png", 
            "is_dir": false, 
            "icon": "page_white_picture", 
            "root": "dropbox", 
            "client_mtime": "Thu, 21 Jun 2012 01:31:19 +0000", 
            "revision": 26154
        }, 
        {
            "size": "0 bytes", 
            "rev": "c0140471f2ee", 
            "thumb_exists": false, 
            "bytes": 0, 
            "modified": "Thu, 17 Jul 2014 21:22:46 +0000", 
            "mime_type": "text/plain", 
            "path": "/Untitled.txt", 
            "is_dir": false, 
            "icon": "page_white_text", 
            "root": "dropbox", 
            "client_mtime": "Thu, 17 Jul 2014 21:22:45 +0000", 
            "revision": 49172
        }, 
        {
            "size": "0 bytes", 
            "rev": "436f0471f2ee", 
            "thumb_exists": false, 
            "bytes": 0, 
            "modified": "Wed, 16 May 2012 02:37:39 +0000", 
            "path": "/Videos", 
            "is_dir": true, 
            "icon": "folder", 
            "root": "dropbox", 
            "revision": 17263
        }, 
        {
            "size": "0 bytes", 
            "rev": "618e0471f2ee", 
            "thumb_exists": false, 
            "bytes": 0, 
            "modified": "Sat, 16 Feb 2013 19:33:15 +0000", 
            "path": "/WindowsFormsApplication3", 
            "is_dir": true, 
            "icon": "folder", 
            "root": "dropbox", 
            "revision": 24974
        }, 
        {
            "size": "0 bytes", 
            "rev": "87bc0471f2ee", 
            "thumb_exists": false, 
            "bytes": 0, 
            "modified": "Tue, 18 Feb 2014 00:02:51 +0000", 
            "path": "/Work Backups", 
            "is_dir": true, 
            "icon": "folder", 
            "root": "dropbox", 
            "revision": 34748
        }, 
        {
            "size": "2.8 KB", 
            "rev": "7d180471f2ee", 
            "thumb_exists": false, 
            "bytes": 2820, 
            "modified": "Mon, 03 Feb 2014 03:17:02 +0000", 
            "mime_type": "text/x-c++src", 
            "path": "/xbox_reader.cpp", 
            "is_dir": false, 
            "icon": "page_white_code", 
            "root": "dropbox", 
            "client_mtime": "Mon, 03 Feb 2014 03:17:10 +0000", 
            "revision": 32024
        }
    ], 
    "size": "0 bytes"
}